{"families":[{"key":"B1_","parents":["B1"],"children":["B3","A45"]},{"key":"A44_A45","parents":["A44","A45"],"children":["A46","A48","A51"]},{"key":"A57_A46","parents":["A57","A46"],"children":["A47"]},{"key":"A48_A56","parents":["A48","A56"],"children":["A50"]},{"key":"A48_A59","parents":["A48","A59"],"children":["A49"]},{"key":"B3_B4","parents":["B3","B4"],"children":["B5","B6"]}],"people":{"B1":{"name":"Jacques","fullname":"Jacques BENCE","born":"1930","died":"2020","classname":"","house":""},"A57":{"name":"Flavien","fullname":"Flavien BOULHO","born":"1982","died":"","classname":"","house":""},"B3":{"name":"Patrick","fullname":"Patrick BENCE","born":"1964","died":"","classname":"","house":""},"A44":{"name":"Bruno","fullname":"Bruno LE NORMAND","born":"1960","died":"","classname":"","house":"Le Normand"},"A45":{"name":"Corinne","fullname":"Corinne BENCE","born":"1959","died":"","classname":"","house":""},"A46":{"name":"Amandine","fullname":"Amandine LE NORMAND","born":"1986","died":"","classname":"","house":"Le Normand"},"A47":{"name":"Ewen","fullname":"Ewen BOULHO","born":"2021","died":"","classname":"","house":""},"A48":{"name":"Dorian","fullname":"Dorian LE NORMAND","born":"1988","died":"","classname":"","house":"Le Normand"},"A50":{"name":"Aïden","fullname":"Aïden LE NORMAND","born":"2022","died":"","classname":"","house":"Le Normand"},"A49":{"name":"Elisa","fullname":"Elisa LE NORMAND","born":"2011","died":"","classname":"","house":"Le Normand"},"A51":{"name":"Eymeric","fullname":"Eymeric LE NORMAND","born":"1994","died":"","classname":"","house":"Le Normand"},"B4":{"name":"Agnès","fullname":"Agnès BRULÉ","born":"1968","died":"","classname":"","house":""},"B5":{"name":"Clara","fullname":"Clara BENCE","born":"1999","died":"","classname":"","house":""},"B6":{"name":"Alexandre","fullname":"Alexandre BENCE","born":"1995","died":"","classname":"","house":""},"A56":{"name":"Charlène","fullname":"Charlène BOIZOT","born":"1988","died":"","classname":"","house":""},"A59":{"name":"Anne-Clarisse","fullname":"Anne-Clarisse ROSSIGNOL","born":"1989","died":"","classname":"","house":""}}}